[
    {
        "fullName": "Господарський суд Дніпропетровської області",
        "region": 3,
        "name": "Господарський суд Дніпропетровської області",
        "nameWhom": "Господарського суду  Дніпропетровської області",
        "index": "49600",
        "street": "вул. Куйбишева, 1а",
        "mobile": "(056)377-18-49"
    },
    {
        "fullName": "Орджонікідзевський районний суд м. Запоріжжя",
        "region": 7,
        "name": "Орджонікідзе р/с м. Запоріжжя",
        "nameWhom": "Орджонікідзевського районного суду м. Запоріжжя",
        "index": "69035",
        "street": "пр. Перемоги, 51",
        "mobile": "(061)234-31-10"
    },
    {
        "fullName": "Жовтневий районний суд м. Запоріжжя",
        "region": 7,
        "name": "Жовтневе р/с м. Запоріжжя",
        "nameWhom": "Жовтневого районного суду м. Запоріжжя",
        "index": "69063",
        "street": "вул.Дзержинського, 6",
        "mobile": "(061)764-40-73"
    },
    {
        "fullName": "Заводський районний суд м. Запоріжжя",
        "region": 7,
        "name": "Заводський р/с м. Запоріжжя",
        "nameWhom": "Заводського районного суду м. Запоріжжя",
        "index": "69009",
        "street": "вул. Лізи Чайкіної, буд. 65",
        "mobile": "(061)236-59-98"
    },
    {
        "fullName": "Комунарський районний суд м. Запоріжжя",
        "region": 7,
        "name": "Комунарський р/с м. Запоріжжя",
        "nameWhom": "Комунарського районного суду м. Запоріжжя",
        "index": "69104",
        "street": "вул. Малиновського, 7",
        "mobile": "(061)289-88-76"
    },
    {
        "fullName": "Ленінський районний суд м. Запоріжжя",
        "region": 7,
        "name": "Ленінський м. Запоріжжя (Р/М)",
        "nameWhom": "Ленінського районного суду м. Запоріжжя",
        "index": "69006",
        "street": "вул. 40 років Радянської України 1/2",
        "mobile": "(061)283-08-13"
    },
    {
        "fullName": "Хортицький районний суд м. Запоріжжя",
        "region": 7,
        "name": "Хортицький м. Запоріжжя (Р/М)",
        "nameWhom": "Хортицького районного суду м. Запоріжжя",
        "index": "69076",
        "street": "пр-т. Ювілейний, 33",
        "mobile": "(061)224-95-73"
    },
    {
        "fullName": "Шевченківський районний суд м. Запоріжжя",
        "region": 7,
        "name": "Шевченківський м. Запоріжжя (Р/М)",
        "nameWhom": "Шевченківського районного суду м. Запоріжжя",
        "index": "69071",
        "street": "вул. Чарівна, буд. 117-А",
        "mobile": "(061)222-26-03"
    },
    {
        "fullName": "Енергодарський міський суд Запорізької обл.",
        "region": 7,
        "name": "Енергодарський м/с Запорізької обл.",
        "nameWhom": "Енергодарського міського суду Запорізької обл.",
        "index": "71504",
        "street": "пр-т. Будівельників, 17",
        "mobile": "(06139)3-19-01"
    },
    {
        "fullName": "Бердянський міськрайонний суд Запорізької обл.",
        "region": 7,
        "name": "Бердянський міськрайонний Запорізької обл. (М/Р)",
        "nameWhom": "Бердянського міськрайонного суду Запорізької обл.",
        "index": "71118",
        "street": "вул. Комунарів, 64",
        "mobile": "(06153)3-56-34"
    },
    {
        "fullName": "Мелітопольський міськрайонний суд Запорізької обл.",
        "region": 7,
        "name": "Мелітопольський міськрайонний Запорізької обл. (М/Р)",
        "nameWhom": "Мелітопольського міськрайонного суду  Запорізької обл.",
        "index": "",
        "street": "Шмідта, 11,  Дзержинського, 90",
        "mobile": "(0619)43-84-93"
    },
    {
        "fullName": "Якимівський районний суд Запорізької обл.",
        "region": 7,
        "name": "Якимівський Запорізької обл. (Р/С)",
        "nameWhom": "Якимівського районного суду Запорізької обл.",
        "index": "72503",
        "street": "Пушкіна, 25",
        "mobile": "(06131)9-16-67"
    },
    {
        "fullName": "Чернігівський районний суд Запорізької обл.",
        "region": 7,
        "name": "Чернігівський Запорізької обл.(Р/С)",
        "nameWhom": "Чернігівського районного суду Запорізької обл.",
        "index": "71202",
        "street": "Леніна, 391",
        "mobile": "(06140)9-10-16"
    },
    {
        "fullName": "Токмацький районний суд Запорізької обл.",
        "region": 7,
        "name": "Токмацький Запорізької обл. (Р/С)",
        "nameWhom": "Токмацького районного суду Запорізької обл.",
        "index": "71701",
        "street": "Леніна, 28",
        "mobile": "(06178)2-31-81"
    },
    {
        "fullName": "Розівський районний суд Запорізької обл.",
        "region": 7,
        "name": "Розівський Запорізької обл. (Р/С)",
        "nameWhom": "Розівського районного суду Зпорізької обл.",
        "index": "70301",
        "street": "Новобудова, 23",
        "mobile": "(06162)9-73-02, 9-71-31"
    },
    {
        "fullName": "Приморський районний суд Запорізької обл.",
        "region": 7,
        "name": "Приморський Запорізької обл. (Р/С)",
        "nameWhom": "Приморського районного суду Запорізької обл.",
        "index": "72100",
        "street": "Поштова, 6",
        "mobile": "(0237)7-22-30"
    },
    {
        "fullName": "Приазовський районний суд Запорізької обл.",
        "region": 7,
        "name": "Приазовський Запорізької обл. (Р/С)",
        "nameWhom": "Приазовського районного суду Запорізької обл.",
        "index": "72401",
        "street": "Пушкіна, 5",
        "mobile": "(06133)2-21-60, 2-22-77"
    },
    {
        "fullName": "Пологівський районний суд Запорізької обл.",
        "region": 7,
        "name": "Пологівський Запорізької обл. (Р/С)",
        "nameWhom": "Пологівського районного суду Запорізької обл.",
        "index": "70600",
        "street": "М. Горького, 28",
        "mobile": "(06165)2-28-11"
    },
    {
        "fullName": "Оріхівський районний суд Запорізької обл.",
        "region": 7,
        "name": "Оріхівський Запорізької обл. (Р/С)",
        "nameWhom": "Оріхівського районного суду Запорізької обл.",
        "index": "70500",
        "street": "Першотравнева, 23",
        "mobile": "(0241)4-36-23"
    },
    {
        "fullName": "Новомиколаївський районний суд Запорізької обл.",
        "region": 7,
        "name": "Новомиколаївський Запорізької обл. (Р/С)",
        "nameWhom": "Новомиколаївського районного суду Запорізької обл.",
        "index": "70100",
        "street": "Горького, 11",
        "mobile": "(06144)9-18-05"
    },
    {
        "fullName": "Михайлівський районний суд Запорізької обл.",
        "region": 7,
        "name": "Михайлівський Запорізької обл. (Р/С)",
        "nameWhom": "Михайлівського районного суду  Запорізької обл. ",
        "index": "72002",
        "street": "Артезіанська 6-а",
        "mobile": "(0232)2-02-10, 2-16-22"
    },
    {
        "fullName": "Куйбишевський районний суд Запорізької обл.",
        "region": 7,
        "name": "Куйбишевский Запорізької обл. (Р/С)",
        "nameWhom": "Куйбишевського районного суду Запорізької обл.",
        "index": "71001",
        "street": "Леніна, 26-А",
        "mobile": "(06147)2-13-58"
    },
    {
        "fullName": "Кам'янсько-Дніпровський районний суд Запорізької обл.",
        "region": 7,
        "name": "Кам'янсько-Дніпровський Запорізької обл. (Р/С)",
        "nameWhom": "Кам'янсько-Дніпровського рійонного суду Запорізької обл.",
        "index": "71304",
        "street": "Йожикова, 93",
        "mobile": "(06138)2-39-08"
    },
    {
        "fullName": "Запорізький районний суд Запорізької обл.",
        "region": 7,
        "name": "Запорізький Запорізької обл. (Р/С)",
        "nameWhom": "Запорізького районного суду Запорізької обл.",
        "index": "69089",
        "street": "Істоміна, 10, Істоміна, 37",
        "mobile": "(061)222-10-33, 278-55-14"
    },
    {
        "fullName": "Гуляйпільський районний суд Запорізької обл.",
        "region": 7,
        "name": "Гуляйпільський Запорізької обл. (Р/С)",
        "nameWhom": "Гуляйпільського районного суду Запорізької обл.",
        "index": "70200",
        "street": "вул. 9 січня, буд. 31",
        "mobile": "(06145)4-11-59"
    },
    {
        "fullName": "Вільнянсьький районний суд Запорізької обл.",
        "region": 7,
        "name": "Вільнянський Запорізької обл. (Р/С)",
        "nameWhom": "Вільнянського районного суду Запорізької обл.",
        "index": "70002",
        "street": "Бочарова, 4",
        "mobile": "(06143)4-13-76"
    },
    {
        "fullName": "Веселівський районний суд Запорізької обл.",
        "region": 7,
        "name": "Веселвський Запорізької обл. (Р/С)",
        "nameWhom": "Веселівського районного суду Запорізької обл.",
        "index": "72202",
        "street": "Леніна, 135",
        "mobile": "(06136)2-13-51"
    },
    {
        "fullName": "Великобілозерський районний суд Запорізької обл.",
        "region": 7,
        "name": "Великобілозерський Запорізької обл. (Р/С)",
        "nameWhom": "Великобілозерського районного суду Запорізької обл.",
        "index": "71401",
        "street": "Пархоменка, 193",
        "mobile": "20281, 20356, 20273"
    },
    {
        "fullName": "Василівський районний суд Запорізької обл.",
        "region": 7,
        "name": "Василівський Запорізької обл. (Р/С)",
        "nameWhom": "Василівського районного суду Запорізької обл.",
        "index": "71600",
        "street": "Радянська, 2",
        "mobile": "(06175)7-26-19, 7-26-29"
    },
    {
        "fullName": "Запорізький окружний адміністративний суд",
        "region": 7,
        "name": "Запорізький окружний адміністративний суд (ОА/С)",
        "nameWhom": "Запорізького окружного адміністративного суду",
        "index": "69041",
        "street": "Кремлівська, 65-В",
        "mobile": "(061)286-50-15"
    },
    {
        "fullName": "Господарський суд Запорізької обл.",
        "region": 7,
        "name": "Господарський Запорізької обл. (Г/С)",
        "nameWhom": "Господарського суду Запорізької обл.",
        "index": "69001",
        "street": "Тюленіна, 21, Шаумяна, 4",
        "mobile": "(061)224-08-88"
    },
    {
        "fullName": "Апеляційний суд Запорізької обл.",
        "region": 7,
        "name": "Апеляційний  Запорізької обл. (А/С)",
        "nameWhom": "Апеляційного суду Запорізької обл.",
        "index": "69005",
        "street": "Леніна, 162",
        "mobile": "(061)218-42-34"
    },
    {
        "fullName": "Приморський районний суд м. Маріуполя Донецької обл.",
        "region": 4,
        "name": "Приморський м. Маріуполя Донецької обл. (Р/М)",
        "nameWhom": "Приморського районного суду м. Маріуполя Донецької обл.",
        "index": "87525",
        "street": "пр-т Будівельників, 52-А",
        "mobile": "(0629)37-21-90, 37-97-29"
    },
    {
        "fullName": "Орджонікідзевський районний суд м. Маріуполя Донецької обл.",
        "region": 4,
        "name": "Орджонікідзевський м. Маріуполя Донецької обл. (Р/М)",
        "nameWhom": "Орджонікідзевського районного суду м. Маріупіль Донепцької обл.",
        "index": "87545",
        "street": "пр-т Перемоги, 68",
        "mobile": "(0629)23-53-59"
    },
    {
        "fullName": "Іллічівський районний суд м. Маріуполя Донецької обл.",
        "region": 4,
        "name": "Іллічівський м. Маріуполя Донецької обл. (Р/М)",
        "nameWhom": "Іллічівського районного суду м. Маріуполя Донецької обл.",
        "index": "87535",
        "street": "пр-т Металургів,231",
        "mobile": "(0629)47-28-69"
    },
    {
        "fullName": "Жовтневий районний суд м. Маріуполя Донецької обл.",
        "region": 4,
        "name": "Жовтневий м. Маріуполя Донецької обл. (Р/М)",
        "nameWhom": "Жовтневого районного суду м. Маріуполя Донецької обл.",
        "index": "87500",
        "street": "пр-т Металургів,31",
        "mobile": "(0629)33-13-72, 33-30-12"
    },
    {
        "fullName": "Червоногвардійський районний суд м. Макіївка Донецької обл.",
        "region": 4,
        "name": "Червоногвардійський м. Макіївка Донецької обл. (Р/М)",
        "nameWhom": "Червоногвардійського районного суду м. Макіївка Донецької обл.",
        "index": "86121",
        "street": "пров. Тореза,49",
        "mobile": "(0623)24-17-55"
    },
    {
        "fullName": "Центрально-Міський районний суд м. Макіївка Донецької обл.",
        "region": 4,
        "name": "Центрально-Міський м. Макіївка Донецької обл. (Р/М)",
        "nameWhom": "Центрально-Міського районного суду м. Макіївка Донецької обл.",
        "index": "86108",
        "street": "Свердлова, 111",
        "mobile": "(0623)26-13-43, 22-08-70,22-29-90"
    },
    {
        "fullName": "Совєтський районний суд м. Макіївка Донецької обл.",
        "region": 4,
        "name": "Совєтський м. Макіївка Донецької обл. (Р/М)",
        "nameWhom": "Совєтського районного суду м. Макіївка Донецької обл.",
        "index": "86145",
        "street": "Декабристів, 14",
        "mobile": "(0623)23-39-86"
    },
    {
        "fullName": "Кіровський районний суд м. Макіївка Донецької обл.",
        "region": 4,
        "name": "Кіровський м. Макіївка Донецької обл. (Р/М)",
        "nameWhom": "Кіровського районного суду м. Макіївка Донецької обл.",
        "index": "86101",
        "street": "Димитрова,1",
        "mobile": "(0623)26-45-67, 21-46-18"
    },
    {
        "fullName": "Гірницький районний суд м. Макіїївка Донецької обл.",
        "region": 4,
        "name": "Гірницький м. Макіївка Донецької обл. (Р/М)",
        "nameWhom": "Гірницького районного суду м. Макіївка Донецької обл.",
        "index": "86103",
        "street": "пр-т Генерала Данилова, 21",
        "mobile": "(0623)22-15-42"
    },
    {
        "fullName": "Пролетарський районний суд м. Донецька",
        "region": 4,
        "name": "Пролетарський м. Донецька (Р/М)",
        "nameWhom": "Пролетарського районного суду м. Донецька",
        "index": "83044",
        "street": "вул.Літке, 10",
        "mobile": "(062)222-40-37"
    },
    {
        "fullName": "Петровський районний суд м. Донецька",
        "region": 4,
        "name": "Петровський м. Донецька (Р/М)",
        "nameWhom": "Петровського районного суду м. Донецька",
        "index": "83111",
        "street": "Салтикова-Щедріна, 1-а",
        "mobile": "(062)203-31-19"
    },
    {
        "fullName": "Ленінський районний суд м. Донецька",
        "region": 4,
        "name": "Ленінський м. Донецька (Р/М)",
        "nameWhom": "Ленінського районного суду м. Донецька",
        "index": "83062",
        "street": "Аксакова, 56",
        "mobile": "(062)266-13-01, 266-21-01"
    },
    {
        "fullName": "Куйбишевський районний суд м. Донецька",
        "region": 4,
        "name": "Куйбишевський  м. Донецька (Р/М)",
        "nameWhom": "Куйбишевського районного суду м. Донецька",
        "index": "83012",
        "street": "Соколінна, 1",
        "mobile": "(062)253-36-40"
    },
    {
        "fullName": "Кіровський районний суд м. Донецька",
        "region": 4,
        "name": "Кіровський м. Донецька (Р/М)",
        "nameWhom": "Кіровського районного суду м. Донецька",
        "index": "83095",
        "street": "Юності, 22",
        "mobile": "(062)277-06-85"
    },
    {
        "fullName": "Київський районний суд м. Донецька",
        "region": 4,
        "name": "Київський м. Донецька (Р/М)",
        "nameWhom": "Київського районного суду м. Донецька",
        "index": "83054",
        "street": "Собінова, 147",
        "mobile": "(062)258-32-45"
    },
    {
        "fullName": "Калінінський районний суд м. Донецька",
        "region": 4,
        "name": "Калінінський м. Донецька (Р/М)",
        "nameWhom": "Калініського районного суду м. Донецька",
        "index": "83052",
        "street": "пр-т Миру, 52",
        "mobile": "(062) 294-11-24"
    },
    {
        "fullName": "Ворошиловський районний суд м. Донецька",
        "region": 4,
        "name": "Ворошиловський м. Донецьк (Р/М)",
        "nameWhom": "Ворошиловського районного суду м. Донецька",
        "index": "83015",
        "street": "вул. Любавіна, 4, 4й, 5й поверх",
        "mobile": "(062)338-43-39, 338-43-28"
    },
    {
        "fullName": "Будьоннівський районний суд м. Донецька",
        "region": 4,
        "name": "Будьоннівський м. Донецька (Р/М)",
        "nameWhom": "Будьоннівського районного суду м. Донецька",
        "index": "83058",
        "street": "Арктики, 20",
        "mobile": "(062)ХХХХХХХХ"
    },
    {
        "fullName": "Центрально-Міський районний суд м. Горлавка, донецької обл.",
        "region": 4,
        "name": "Центрано-Міський м. Горлівка, Донецької обл. (Р/М)",
        "nameWhom": "Центрально-Міського районного суду м. Горлівка Донецької обл.",
        "index": "84601",
        "street": "Леніна, 1",
        "mobile": "(06242)4-83-42"
    },
    {
        "fullName": "Микитівський районний суд м. Горлівка Донецької обл.",
        "region": 4,
        "name": "Микитівський м. Горлівка (Р/М)",
        "nameWhom": "Микитівського  районного суду м. Горлівка, Донецької обл. ",
        "index": "84635",
        "street": "Черняховського, 75",
        "mobile": "(06242)6-62-80, 6-66-76"
    },
    {
        "fullName": "Калинінський районний суд м. Горлівка Донецької обл.",
        "region": 4,
        "name": "Калинінський м. Горлівка (Р/М)",
        "nameWhom": "Калинінського районного суду м. Горлівка Донецької обл.",
        "index": "84609",
        "street": "Горлівської дивізії, 79",
        "mobile": "(06242)4-34-55"
    },
    {
        "fullName": "Харцизький міський суд Донецької обл.",
        "region": 4,
        "name": "Харцизький Донецької обл. (М/С)",
        "nameWhom": "Харцизького міського суду Донецької обл.",
        "index": "86700",
        "street": "пров. Коні, 2",
        "mobile": "(06257)4-28-64"
    },
    {
        "fullName": "Торезький міський суд Донецької обл.",
        "region": 4,
        "name": "Торезький Донецької обл. (М/С)",
        "nameWhom": "Торезького міського суду Донецької обл.",
        "index": "86600",
        "street": "Пушкіна, 15",
        "mobile": "(06254)3-24-34"
    },
    {
        "fullName": "Сніжнянський міський суд Донецької обл",
        "region": 4,
        "name": "Сніжнянський  Донецької обл. (М/С)",
        "nameWhom": "Сніжнянського міського суду Донецької обл.",
        "index": "86500",
        "street": "Леніна, 38",
        "mobile": "(06256)5-37-04"
    },
    {
        "fullName": "Селидівський міський суд Донецької обл.",
        "region": 4,
        "name": "Селидівський Донецької обл (М/С)",
        "nameWhom": "Селидівського міського суду Донецької обл.",
        "index": "85400",
        "street": "Пушкіна,4",
        "mobile": "(06237)7-22-41"
    },
    {
        "fullName": "Новогродівський міський суд Донецької обл.",
        "region": 4,
        "name": "Новогродівський Донецької обл. (М/С)",
        "nameWhom": "Новогродівського міського суду Донецької обл.",
        "index": "85483",
        "street": "Риночна, 110",
        "mobile": "(06237)3-40-51"
    },
    {
        "fullName": "Краснолиманський міський суд Донецької обл.",
        "region": 4,
        "name": "Краснолиманський Донецької обл. (М/С)",
        "nameWhom": "Краснолиманського міського суду Донецької обл.",
        "index": "84400",
        "street": "Фрунзе,13",
        "mobile": "(06261)4-15-55"
    },
    {
        "fullName": "Краматорський міський суд Донецької обл.",
        "region": 4,
        "name": "Краматорський Донецької обл. (М/С)",
        "nameWhom": "Краматорського міського суду Донецької обл.",
        "index": "84333",
        "street": "Маяковського,21",
        "mobile": "(0626) 44-28-54"
    },
    {
        "fullName": "Кіровський міський суд Донецької обл.",
        "region": 4,
        "name": "Кіровський Донецької обл. (М/С)",
        "nameWhom": "Кіровського міського суду Донецької обл.",
        "index": "86300",
        "street": "Піонерська, 2",
        "mobile": "(06250) 6-21-26"
    },
    {
        "fullName": "Жданівський міський суд Донецької обл.",
        "region": 4,
        "name": "Жданівський Донецької обл. (М/С)",
        "nameWhom": "Жданівського міського суду Донецької обл.",
        "index": "86391",
        "street": "Комсомолька, 11",
        "mobile": "(06250) 7-29-51"
    },
    {
        "fullName": "Єнакіївський міський суд Донецької обл.",
        "region": 4,
        "name": "Єнакіївський  Донецької обл. (М/С)",
        "nameWhom": "Єнакіївського міського суду Донецької обл.",
        "index": "86429",
        "street": "Свердлова,118",
        "mobile": "(06252) 2-28-38"
    },
    {
        "fullName": "Дружківський міський суд Донецької обл.",
        "region": 4,
        "name": "Дружківський Донецької обл. (М/С)",
        "nameWhom": "Дружківського міського суду Донецької обл.",
        "index": "84205",
        "street": "Енгельса, 45",
        "mobile": "(06267) 4-21-62"
    },
    {
        "fullName": "Докучаєвський міський суд Донецької обл.",
        "region": 4,
        "name": "Докучаєвський Донецької обл. (М/С)",
        "nameWhom": "Докучаєвського міського суду Донецької обл.",
        "index": "85740",
        "street": "Центральна, 44-А",
        "mobile": "(06275) 3-11-08"
    },
    {
        "fullName": "Димитровський міський суд Донецької обл.",
        "region": 4,
        "name": "Димитровський Донецької обл (М/С)",
        "nameWhom": "Димитровського міського суду Донецької обл.",
        "index": "85323",
        "street": "Артема, 73",
        "mobile": "(06239) 6-43-31"
    },
    {
        "fullName": "Дзержинський міський суд Донецької обл.",
        "region": 4,
        "name": "Дзержинський Донецької обл (М/С)",
        "nameWhom": "Дзержинського міського суду Донецької обл.",
        "index": "85200",
        "street": "50-річчя Жовтня, 4",
        "mobile": "(06247) 4-37-29"
    },
    {
        "fullName": "Дебальцевський міський суд Донецької обл.",
        "region": 4,
        "name": "Дебальцевський Донецької обл. (М/С)",
        "nameWhom": "Дебальцевського міського суду Донецької обл.",
        "index": "84700",
        "street": "Радянська, 35",
        "mobile": "(06249) 2-22-39, 2-37-22"
    },
    {
        "fullName": "Вугледарський міський суд Донецької обл.",
        "region": 4,
        "name": "Вугледарський Донецької обл (М/С)",
        "nameWhom": "Вугледарського міського суду Донецької обл.",
        "index": "85670",
        "street": "Трифонова, 22",
        "mobile": "(06273) 6-44-66, 6-57-55"
    },
    {
        "fullName": "Авдіївський міський суд Донецької обл.",
        "region": 4,
        "name": "Авдіївський Донецької обл. (М/С)",
        "nameWhom": "Авдіївського міського суду Донецької обл.",
        "index": "86065",
        "street": "Комунальна, 14",
        "mobile": "(06236) 7-14-27"
    },
    {
        "fullName": "Ясинуватський міськрайонний суд Донецької обл.",
        "region": 4,
        "name": "Ясинуватський міськрайонний Донецької обл.(М/Р)",
        "nameWhom": "Ясинуватського міськрайонного суду Донецької обл.",
        "index": "86006",
        "street": "вул.Заводська, 90",
        "mobile": "(06236) 4-28-81"
    },
    {
        "fullName": "Шмахтарський міськрайонний суд Донецької обл.",
        "region": 4,
        "name": "Шахтарський міськрайонний Донецької обл. (М/Р)",
        "nameWhom": "Шахтарського міськрайонного суду Донецької обл.",
        "index": "86211",
        "street": "Крупської, 7-А",
        "mobile": "(06255) 4-52-85"
    },
    {
        "fullName": "Слов'янський міськрайонний суд Донецької обл.",
        "region": 4,
        "name": "Слов'янський міськрайонний Донецької обл. (М/Р)",
        "nameWhom": "Слов'янського міськрайонного суду Донецької обл.",
        "index": "84122",
        "street": "Добровольського, 2",
        "mobile": "(06262) 2-71-77"
    },
    {
        "fullName": "Красноармійський міськрайонний суд Донецької обл.",
        "region": 4,
        "name": "Красноармійський міськрайонний Донецької обл. (М/Р)",
        "nameWhom": "Красноармійського міськрайонного суду Донецької обл.",
        "index": "85300",
        "street": "Горького, 20",
        "mobile": "(06239) 2-02-65"
    },
    {
        "fullName": "Костянтинівський міськрайонний суд Донецької обл.",
        "region": 4,
        "name": "Костянтинівський міськрайонний Донецької обл. (М/Р)",
        "nameWhom": "Костянтинівського міськрайонного суду Донецької обл.",
        "index": "85110",
        "street": "пр-т Ломоносова, 157",
        "mobile": "(06272) 2 59 11"
    },
    {
        "fullName": "Добропільський міськрайонний суд Донецької обл.",
        "region": 4,
        "name": "Добропільський міськрайонний Донецької обл. (М/Р)",
        "nameWhom": "Добропільського міськрайонного суду Донецької обл.",
        "index": "85004",
        "street": "Радянська, 39-А",
        "mobile": "(06277) 2-88-25"
    },
    {
        "fullName": "Артемівський міськрайонний суд Донецької обл.",
        "region": 4,
        "name": "Артемівський міськрайонний Донецької обл. (М/Р)",
        "nameWhom": "Артемівського міськрайонного суду Донецької обл.",
        "index": "84500",
        "street": "Артема, 5",
        "mobile": "(06274) 44 - 17 - 74 "
    },
    {
        "fullName": "Тельманівський районний суд Донецької обл.",
        "region": 4,
        "name": "Тельманівський Донецької обл. (Р/С)",
        "nameWhom": "Тельманівського районного суду Донецької обл.",
        "index": "87100",
        "street": "пр-т Тельмана, 1",
        "mobile": "(06279) 5-18-35"
    },
    {
        "fullName": "Старобешівський районний суд Донецької обл.",
        "region": 4,
        "name": "Старобешівський Донецької обл. (Р/С)",
        "nameWhom": "Старобешівського районного суду Донецької обл.",
        "index": "87200",
        "street": "Поштова, 29",
        "mobile": "(06253) 2-19-76"
    },
    {
        "fullName": "Першотравневий районний суд Донецької обл. ",
        "region": 4,
        "name": "Першотравневий Донецької обл. (Р/С)",
        "nameWhom": "Першотравневого районного суду Донецької обл.",
        "index": "87400",
        "street": "Котанова, 102",
        "mobile": "(06297) 2-44-04"
    },
    {
        "fullName": "Олександрівський районний суд Донецької обл.",
        "region": 4,
        "name": "Олександрівський Донецької обл. (Р/С)",
        "nameWhom": "Олександрівського районного суду Донецької обл.",
        "index": "84000",
        "street": "Шкільна, 1",
        "mobile": "(06269) 2-14-64, 2-19-22"
    },
    {
        "fullName": "Новоазовський районний суд Донецької обл.",
        "region": 4,
        "name": "Новоазовський Донецької обл. (Р/С)",
        "nameWhom": "Новоазовського районного суду Донецької обл.",
        "index": "87601",
        "street": "Комунарів, 40-А",
        "mobile": "(06296) 3-16-92"
    },
    {
        "fullName": "Мар'їнський районний суд Донецької обл.",
        "region": 4,
        "name": "Мар'їнський Донецької обл. (Р/С)",
        "nameWhom": "Мар'їнського районного суду Донецької обл.",
        "index": "85600",
        "street": "Леніна, 7",
        "mobile": "(06278) 5-10-39"
    },
    {
        "fullName": "Володарський районний суд Донецької обл.",
        "region": 4,
        "name": "Володарський Донецької обл. (Р/С)",
        "nameWhom": "Володарського районного суду Донецької обл.",
        "index": "87000",
        "street": "пров. Чапаєва, 3",
        "mobile": "(06246) 2-14-33"
    },
    {
        "fullName": "Волноваський районний суд Донецької обл.",
        "region": 4,
        "name": "Волноваський Донецької обл. (Р/С)",
        "nameWhom": "Волноваського районного суду Донецької обл.",
        "index": "85700",
        "street": "Ювілена, 29",
        "mobile": "(06244) 4-53-30, 4-53-39 "
    },
    {
        "fullName": "Великоновосілківський районний суд Донецької обл.",
        "region": 4,
        "name": "Великоновосілківський Донецької обл. (Р/С)",
        "nameWhom": "Великоновосілківського районного суду Донецької обл.",
        "index": "85500",
        "street": "Фонтанна, 21",
        "mobile": "(06243) 2-17-73"
    },
    {
        "fullName": "Амвросіївський районний суд Донецької обл.",
        "region": 4,
        "name": "Амвросіївський Донецької обл. (Р/С)",
        "nameWhom": "Амвросіївського районного суду Донецької обл.",
        "index": "87300",
        "street": "Кірова, 4",
        "mobile": "(06259) 2-31-90"
    },
    {
        "fullName": "Донецький Окружний адміністративний  суд",
        "region": 4,
        "name": "Донецький  Окружний адміністративний суд (ОА/С)",
        "nameWhom": "Донецького Окружного адміністративного суду",
        "index": "83012",
        "street": "50-ї Гвардійської дивізії , 17",
        "mobile": "(062)388 19 16"
    },
    {
        "fullName": "Господарський суд Донецької обл.",
        "region": 4,
        "name": "Господарський  Донецької обл. (Г/С)",
        "nameWhom": "Господарського суду Донецької обл.",
        "index": "83048",
        "street": "Артема, 157",
        "mobile": "(062) 305-60-41"
    },
    {
        "fullName": "Апеляційний суд Донецької області у м.Маріуполі",
        "region": 4,
        "name": "Апеляційний  Донецької області у м.Маріуполі (А/С)",
        "nameWhom": "Апеляційного суду Донецької області у м.Маріуполі",
        "index": "87500",
        "street": "Леніна, 1-а",
        "mobile": "(0629) 53-04-84, 33-21-62"
    },
    {
        "fullName": "Апеляційний суд Донецької обл. у м. Донецьк",
        "region": 4,
        "name": "Апеляційний Донецької обл. у м. Донецьк (А/С)",
        "nameWhom": "Апеляційного суду Донецької обл. у м. Донецьк",
        "index": "83015",
        "street": "Майдан Правосуддя, 1",
        "mobile": "(062) 340-76-65"
    },
    {
        "fullName": "Донецький апеляційний адміністративний суд ",
        "region": 4,
        "name": "Донецький апеляційний адміністративний суд (АА/С)",
        "nameWhom": "Донецького апеляційного адміністративного суду.",
        "index": "83017",
        "street": "бульвар Шевченка, 26",
        "mobile": "(062) 332-19-00"
    },
    {
        "fullName": "Донецький апеляційний господарський суд",
        "region": 4,
        "name": "Донецький апеляційний господарський суд (АГ/С)",
        "nameWhom": "Донецького апеляційного господарського суду",
        "index": "83048",
        "street": "Артема, 157",
        "mobile": "(062) 332-57-40 , 332-57-45 "
    },
    {
        "fullName": "Городоцький районний суд Львівської області",
        "region": 13,
        "name": "Городоцький р/с Львівської",
        "nameWhom": "Городоцького районного суду Львівської області",
        "index": "81500",
        "street": "майдан Гайдамаків, буд. 30",
        "mobile": "03231 3 05 30"
    },
    {
        "fullName": "Придніпровський районний суд м.Черкаси",
        "region": 14,
        "name": "Придніпровський р/с",
        "nameWhom": "Придніпровського районного суду м.Черкаси",
        "index": "18015",
        "street": "вул. Гоголя, 316 (третій поверх)",
        "mobile": ""
    },
    {
        "fullName": "Київський районний суд м. Одеси",
        "region": 15,
        "name": "Київський р/с м. Одеси",
        "nameWhom": "Київського районного суду м. Одеси",
        "index": "65080",
        "street": "вул.Варненська,3б",
        "mobile": "0482718-99-43"
    },
    {
        "fullName": "Сокальський районний суд Львівської області",
        "region": 13,
        "name": "Сокальський р/с Львівської обл.",
        "nameWhom": "Сокальського районного суду Львівської області",
        "index": "80000",
        "street": "пл. Січових Стрільців, 19",
        "mobile": "03257 7 22 05"
    },
    {
        "fullName": "Шевченківський районний суд міста Києва",
        "region": 9,
        "name": "Шевченківський р/с",
        "nameWhom": "Шевченківського районного суду міста Києва",
        "index": "04655",
        "street": "вул. Смирнова-Ласточкіна, 10-б",
        "mobile": ""
    },
    {
        "fullName": "Червонозаводський районний суд м. Харкова",
        "region": 21,
        "name": "Червонозаводський р/с Харкова",
        "nameWhom": "Червонозаводського районного суду м. Харкова",
        "index": "61001",
        "street": "майдан Руднєва, 36, 3 підїзд",
        "mobile": "057 733 34 54"
    },
    {
        "fullName": "Печерський районний суд міста Києва",
        "region": 9,
        "name": "Печерський р/с",
        "nameWhom": "Печерського  районного суду міста Києва",
        "index": "01601",
        "street": "вул. Хрещатик, 42-А",
        "mobile": "044 235 32 78"
    },
    {
        "fullName": "Солом’янський районний суд м. Києва",
        "region": 9,
        "name": "Соломянський р/с",
        "nameWhom": "Солом’янського районного суду м. Києва",
        "index": "03680",
        "street": "вул. Максима Кривоноса, 25",
        "mobile": ""
    },
    {
        "fullName": "Дзержинський районний суд м. Харкова",
        "region": 21,
        "name": "Дзержинський р/м Харкова",
        "nameWhom": "Дзержинського районного суду м. Харкова",
        "index": "61202",
        "street": "проспект Перемоги, 52-В",
        "mobile": "057 336 8270"
    },
    {
        "fullName": "Полтавський районний суд Полтавської області",
        "region": 16,
        "name": "Полтавський р/с обл.",
        "nameWhom": "Полтавського районного суду Полтавської області",
        "index": "36008",
        "street": "вул. Фрунзе, 154-а",
        "mobile": "0532 678767"
    },
    {
        "fullName": "Новоселицький районний суд Чернівецької області",
        "region": 25,
        "name": "Новоселицький р/с Чернівецької обл.",
        "nameWhom": "Новоселицького районного суд уЧернівецької області",
        "index": "60300",
        "street": "вул. 1 Травня, 4а",
        "mobile": "0373321934"
    },
    {
        "fullName": "Амур-Нижньодніпровський районний суд м. Дніпропетровська",
        "region": 3,
        "name": "Амур-Нижньодніпровський районний суд м. Дніпропетровська",
        "nameWhom": "Амур-Нижньодніпровського районного суду м. Дніпропетровська",
        "index": "49083",
        "street": "вул. Новоселівська, 9",
        "mobile": "0562 238618"
    },
    {
        "fullName": "Іллічівський міський суд Одеської області",
        "region": 15,
        "name": "Іллічівський м/с Одеської обл.",
        "nameWhom": "Іллічівського міського суду Одеської області",
        "index": "68000",
        "street": "вул. Праці, 10",
        "mobile": ""
    },
    {
        "fullName": "Малинівський районний суд м. Одеса",
        "region": 15,
        "name": "Малинівський р/с м. Одеса",
        "nameWhom": "Малинівського районного суд м. Одеса",
        "index": "65033",
        "street": "вул. Василя, Стуса, 1а",
        "mobile": ""
    },
    {
        "fullName": "Комсомольський районний суд м. Херсона",
        "region": 22,
        "name": "Комсомольський р/с м. Херсона",
        "nameWhom": "Комсомольського районного суду м. Херсона",
        "index": "73000",
        "street": "вул. Маяковського, 6/29",
        "mobile": ""
    },
    {
        "fullName": "Вишгородський районний суд Київської області",
        "region": 10,
        "name": "Вишгородський р/с Київської обл",
        "nameWhom": "Вишгородського районного суду Київської області",
        "index": "7300",
        "street": "вул. Кургузова, 7",
        "mobile": ""
    },
    {
        "fullName": "Овідіопольський районний суд Одеської області",
        "region": 15,
        "name": "Овідіопольський р/с Одеської обл",
        "nameWhom": "Овідіопольського районного суду Одеської області",
        "index": "67801",
        "street": "вул. Берегова. 9",
        "mobile": ""
    },
    {
        "fullName": "Октябрський районний суд м.Полтава",
        "region": 16,
        "name": "Октябрський р/с м.Полтава",
        "nameWhom": "Октябрського районного суду м.Полтава",
        "index": "36002",
        "street": "вул Навроцького, 5",
        "mobile": ""
    },
    {
        "fullName": "Комінтернівський районний суд Одеської області",
        "region": 15,
        "name": "Комінтернівський р/с Одеської обл",
        "nameWhom": "Комінтернівського районного суду Одеської області",
        "index": "67500",
        "street": "вул. Центральна, 83",
        "mobile": ""
    },
    {
        "fullName": "Дарницький районний суд м. Києва",
        "region": 9,
        "name": "Дарницький р/с",
        "nameWhom": "Дарницького районного суду м. Києва",
        "index": "02099",
        "street": "вул. Севастопольська, 14",
        "mobile": ""
    },
    {
        "fullName": "Апостолівський районний суд Дніпропетровської області",
        "region": 3,
        "name": "Апостолівський р/с Дніпропетровської обл.",
        "nameWhom": "Апостолівського районного суду Дніпропетровської області",
        "index": "53802",
        "street": "вул. Визволення, 66",
        "mobile": ""
    },
    {
        "fullName": "Центрально-Міський районний суд м. Кривого Рогу",
        "region": 3,
        "name": "Центрально-Міський р/с м. Кривого Рогу",
        "nameWhom": "Центрально-Міського районного суду м. Кривого Рогу",
        "index": "50099",
        "street": "вул. Першотравнева,12",
        "mobile": ""
    },
    {
        "fullName": "Дніпровський районний суд міста Києва",
        "region": 9,
        "name": "Дніпровський р/с",
        "nameWhom": "Дніпровського районного суду міста Києва",
        "index": "02105",
        "street": "вул. Сергієнка, 3",
        "mobile": ""
    },
    {
        "fullName": "Яворівський районний суд Львівської області",
        "region": 13,
        "name": "Яворівський р/с Львівської",
        "nameWhom": "Яворівського районного суду Львівської області",
        "index": "81000",
        "street": "вул. Маковея, 62",
        "mobile": ""
    },
    {
        "fullName": "Личаківський районний суд м. Львова",
        "region": 13,
        "name": "Личаківський р/с м. Львова",
        "nameWhom": "Личаківського районного суду м. Львова",
        "index": "79007",
        "street": "вул. Б.Лепкого, 16",
        "mobile": ""
    },
    {
        "fullName": "Московський районний суд м. Харкова",
        "region": 21,
        "name": "Московський р/с м. Харкова",
        "nameWhom": "Московського районного судг м. Харкова",
        "index": "61005",
        "street": "пр. 50 річчя ВЛКСМ, буд. 38Є",
        "mobile": ""
    },
    {
        "fullName": "Тернівський районний суд м. Кривого Рогу",
        "region": 3,
        "name": "Тернівський р/с м. Кривий Ріг",
        "nameWhom": "Тернівського районного суду м. Кривого Рогу",
        "index": "50083",
        "street": "вул. Ухтомського, 23",
        "mobile": ""
    },
    {
        "fullName": "Голосіївський районний суд м. Києва",
        "region": 9,
        "name": "Голосіївський р/с м. Києва",
        "nameWhom": "Голосіївського районного суду м. Києва",
        "index": "03127",
        "street": "вул. Полквника Потєхіна, 14-а",
        "mobile": ""
    },
    {
        "fullName": "Бабушкінський районний суд м. Дніпропетровська",
        "region": 3,
        "name": "Бабушкінський р/с м. Дніпропетровська",
        "nameWhom": "Бабушкінського районного суду м. Дніпропетровська",
        "index": "49000",
        "street": "пр. Карла Маркса, 57",
        "mobile": ""
    },
    {
        "fullName": "Кіровський районний суд м. Дніпропетровська",
        "region": 3,
        "name": "Кіровський р/с м. Дніпропетровська",
        "nameWhom": "Кіровського районного суду м. Дніпропетровська",
        "index": "49101",
        "street": "проспект Пушкіна. 29",
        "mobile": ""
    },
    {
        "fullName": "Миколаївський районний суд Львівської області",
        "region": 13,
        "name": "Миколаївський р/с Львівської обл.",
        "nameWhom": "Миколаївського районного суду Львівської області",
        "index": "81600",
        "street": "вул. Мазепи, 29",
        "mobile": ""
    },
    {
        "fullName": "Ірпінський міський суд  Київської області",
        "region": 10,
        "name": "Ірпінський м/с Київської обл",
        "nameWhom": "Ірпінського міського суду  Київської області",
        "index": "08200",
        "street": "вул. Мінеральна, буд. 7",
        "mobile": "04597 57 341"
    },
    {
        "fullName": "Оболонський районний суд міста Києва",
        "region": 9,
        "name": "Оболонський р/с Києва",
        "nameWhom": "Оболонського районного суду міста Києва",
        "index": "04212",
        "street": "вул. Маршала Тимошенко, 2-Є",
        "mobile": ""
    },
    {
        "fullName": "Комсомольський міський суд Полтавської області",
        "region": 16,
        "name": "Комсомольський м/с Полтавської обл",
        "nameWhom": "Комсомольського міського суду Полтавської області",
        "index": "39800",
        "street": "вул. Гірників, 17",
        "mobile": ""
    },
    {
        "fullName": "Подільський районний суд м. Києва",
        "region": 9,
        "name": "Подільський р/с м. Києва",
        "nameWhom": "Подільського районного суду м. Києва",
        "index": "04071",
        "street": "вул. Хорива, 21",
        "mobile": ""
    },
    {
        "fullName": "Приморський районний суд м. Одеси",
        "region": 15,
        "name": "Приморський р/с м. Одеса",
        "nameWhom": "Приморського районного суду м. Одеси",
        "index": "65029",
        "street": "вул. Балківська, буд. 33",
        "mobile": ""
    },
    {
        "fullName": "Великомихайлівський районний суд Одеської області",
        "region": 15,
        "name": "Великомихайлівський р/с Одеської обл",
        "nameWhom": "Великомихайлівського районного суду Одеської області",
        "index": "67100",
        "street": "вул. Пушкіна, буд. 2Б",
        "mobile": ""
    },
    {
        "fullName": "Жовтневий районний суд м.Харкова",
        "region": 21,
        "name": "Жовтневий райсуд м.Харкова",
        "nameWhom": "Жовтневого районного суду м.Харкова",
        "index": "61052",
        "street": "Полтавський шлях, 45",
        "mobile": ""
    },
    {
        "fullName": "Автозаводський районний суд м. Кременчука Полтавської області",
        "region": 16,
        "name": "Автозаводський р/с м. Кременчука",
        "nameWhom": "Автозаводського районного суду м. Кременчука Полтавської області",
        "index": "39600",
        "street": "вул. Першотравнева, буд. 29/5",
        "mobile": ""
    },
    {
        "fullName": "Артемівський районний суд м. Луганськ",
        "region": 12,
        "name": "Артемівський р/с",
        "nameWhom": "Артемівського районного суду м. Луганська",
        "index": "91021",
        "street": "вул. Тімірязєва 1-а",
        "mobile": "(0642) 65-22-70"
    },
    {
        "fullName": "Ленінський районний суд міста Севастополя",
        "region": 18,
        "name": "Ленінський р/с",
        "nameWhom": "Ленінського районного суду м. Севастополя",
        "index": "99000",
        "street": "вул. Леніна 31",
        "mobile": "0692 540 261"
    },
    {
        "fullName": "Гагарінський районний суд м. Севатополя",
        "region": 18,
        "name": "Гагарінський р/с",
        "nameWhom": "Гагарінського районного суду м. Севастополя",
        "index": "99045",
        "street": "вул. Вакуленчука 3",
        "mobile": "0692 24 03 41"
    },
    {
        "fullName": "Теребовлянський районний суд Тернопільської області",
        "region": 20,
        "name": "Теребовлянський райсуд",
        "nameWhom": "Теребовлянського районного суду Тернопільської області",
        "index": "48100",
        "street": "Князя Василька. 116",
        "mobile": "(03551)2-19-87, 2-19-98"
    },
    {
        "fullName": "Київський районний суд м. Полтави",
        "region": 16,
        "name": "Київський районний суд м. Полтави",
        "nameWhom": "Київського районного суду м. Полтави",
        "index": "36034",
        "street": "пров. Хорольський, 6",
        "mobile": "(05322) 66-17-63"
    },
    {
        "fullName": "Деснянський районний суд міста Києва",
        "region": 9,
        "name": "Деснянський р/с Києва",
        "nameWhom": "Деснянського районного суду міста Києва",
        "index": "02225",
        "street": "проспект Маяковського, буд. 5-в",
        "mobile": ""
    },
    {
        "fullName": "Шевченківський районний суд м. Львова",
        "region": 13,
        "name": "Шевченківський р/с Львова",
        "nameWhom": "Шевченківського районного суду м. Львова",
        "index": "79000",
        "street": "вул. Січових Стрільців, 12",
        "mobile": "+38 (032) 260-32-89"
    },
    {
        "fullName": "Стрийський міськрайонний суд Львівської області",
        "region": 13,
        "name": "Стрийський м/р суд",
        "nameWhom": "Стрийського міськрайонного суду Львівської області",
        "index": "82400",
        "street": "вул. Валова, 12",
        "mobile": "(03245) 7-06-34"
    },
    {
        "fullName": "Тернопільський міськрайонний суд Тернопільської області",
        "region": 20,
        "name": "Тернопільський м/р суд Тернопільської обл.",
        "nameWhom": "Тернопільського міськрайонного суду Тернопільської області",
        "index": "46003",
        "street": "вул.Котляревського,34",
        "mobile": ""
    },
    {
        "fullName": "Залізничний районний суд м. Львова",
        "region": 13,
        "name": "Залізничний р/с м. Львова",
        "nameWhom": "Залізничного районного суду м. Львова",
        "index": "79013",
        "street": "вул. С. Бандери, буд. 3",
        "mobile": ""
    },
    {
        "fullName": "Дніпровський районний суд м.Дніпродзержинська, Дніпропетровської області",
        "region": 3,
        "name": "Дніпровський р/с м.Дніпродзержинська",
        "nameWhom": "Дніпровського районного суду м.Дніпродзержинська, Дніпропетровської області",
        "index": "51918",
        "street": "вул. Петровського, 166",
        "mobile": ""
    },
    {
        "fullName": "Бориспільський міськрайонний суд Київської обл.",
        "region": 10,
        "name": "Бориспільський м/р суд",
        "nameWhom": "Бориспільського міськрайонного суду Київської області",
        "index": "08300",
        "street": "вул. Київський Шлях , 72",
        "mobile": "(04595) 6-76-19"
    },
    {
        "fullName": "Київський районний суд м. Харкова",
        "region": 21,
        "name": "Київський р/с Харкова",
        "nameWhom": "Київського районного суду м.Харкова",
        "index": "61168",
        "street": "вул.Блюхера, 7б",
        "mobile": ""
    },
    {
        "fullName": "Київський районний суд м.Сімферополя Автономної Республіки Крим",
        "region": 0,
        "name": "Київський р/с м.Сімферополя",
        "nameWhom": "",
        "index": "95017",
        "street": "вул.Воровського,16",
        "mobile": "(80652)24-93-20, 27-31-66"
    },
    {
        "fullName": "Ленінський районний суд м.Харкова",
        "region": 21,
        "name": "Ленінський р/с м.Харкова",
        "nameWhom": "Ленінського районного суду м.Харкова",
        "index": "61052",
        "street": "вул.Полтавський шлях, 20",
        "mobile": ""
    },
    {
        "fullName": "Дніпропетровський районний суд Дніпропетровської області",
        "region": 3,
        "name": "Дніпропетровський р/с",
        "nameWhom": "Дніпропетровського районного суду Дніпропетровської області",
        "index": "52005",
        "street": "вул. Теплична, 7",
        "mobile": "(0562) 27-80-36"
    },
    {
        "fullName": "Томаківський районний суд  Дніпропетровської області",
        "region": 3,
        "name": "Томаківський р/с Дніпропетровської обл.",
        "nameWhom": "Томаківського районного суду Дніпропетровської області",
        "index": "",
        "street": "вул. Леніна 26, вул. Леніна 28",
        "mobile": "05668 2-22-61, 2-32-02"
    },
    {
        "fullName": "Рахівський районний суд Закарпатської області",
        "region": 6,
        "name": "Рахівський р/с",
        "nameWhom": "Рахівського районного суду Закарпатської області",
        "index": "90600",
        "street": "вул. Карпатська, 15",
        "mobile": "0 (3132) 2-22-44"
    },
    {
        "fullName": "Ялтинський міський суд Автономної Республіки Крим",
        "region": 0,
        "name": "Ялтинський м/с АРК",
        "nameWhom": "ЯлтинськогоміськогосудуАвтономної Республіки Крим",
        "index": "98600",
        "street": "вул.Дмитрієва,4",
        "mobile": ""
    },
    {
        "fullName": "Центральний районний суд  м.Миколаєва",
        "region": 14,
        "name": "Центральний Р/С м. Миколаїв",
        "nameWhom": "Центральног районного суду м.Миколаєва",
        "index": "54020",
        "street": "Декабристів 41/12",
        "mobile": "(0512) 58-39-01"
    },
    {
        "fullName": "Жовтневий районний суд м. Дніпропетровська",
        "region": 3,
        "name": "Жовтневий р/с м. Дніпропетровська",
        "nameWhom": "Жовтневого районного суду м. Дніпропетровська",
        "index": "49044",
        "street": "вул.Паторжинського, 18-А",
        "mobile": "(0562) 713-58-29"
    },
    {
        "fullName": "Святошинський районний суд м.Києва",
        "region": 9,
        "name": "Святошинський р/с м.Києва",
        "nameWhom": "Святошинського районного суду м.Києва",
        "index": "03148",
        "street": "вул. Якуба Коласа, 27-А",
        "mobile": ""
    },
    {
        "fullName": "Нікопольський міськрайонний суд Дніпропетровської області",
        "region": 3,
        "name": "Нікопольський м/р",
        "nameWhom": "Нікопольського міськрайонного суду Дніпропетровської області",
        "index": "53213",
        "street": "вул. Шевченка. Буд. 201",
        "mobile": ""
    },
    {
        "fullName": "Зарічний районний суд м.Суми",
        "region": 19,
        "name": "Зарічний р/с м.Суми",
        "nameWhom": "",
        "index": "40030",
        "street": "вул.Академічна,13",
        "mobile": ""
    },
    {
        "fullName": "Солонянський районний суд Дніпропетровської області",
        "region": 3,
        "name": "Солонянський р/с Дніпропетровської обл.",
        "nameWhom": "Солонянського районного суду Дніпропетровської обл.",
        "index": "52400",
        "street": "вул. Строменка, буд. 1-а",
        "mobile": ""
    },
    {
        "fullName": "Білгород-Дністровський міськрайонний суд Одеської області",
        "region": 15,
        "name": "Білгород-Дністровський м/р суд Одеської обл.",
        "nameWhom": "Білгород-Дністровського міськрайонного суду Одеської області",
        "index": "67700",
        "street": "вул. Енгельса, 27",
        "mobile": "(04849) 3-56-11"
    },
    {
        "fullName": "Межівський районний суд Дніпропетровської області",
        "region": 3,
        "name": "Межівський р/с Дніпропетровської обл.",
        "nameWhom": "Межівського районного суду Дніпропетровської області",
        "index": "52900",
        "street": "вул.Московська,21",
        "mobile": "(05630) 62-0-50"
    },
    {
        "fullName": "Костопільський районний суд міста Костопіль",
        "region": 17,
        "name": "Костопільський р/с",
        "nameWhom": "Костопільського районного суду міста Костопіль",
        "index": "35000",
        "street": "вул.Коперніка,14а",
        "mobile": "(03657)2-36-52"
    },
    {
        "fullName": "Хмельницький міськрайонний суд Хмельницької області",
        "region": 23,
        "name": "Хмельницький мр/с  Хмельницької обл",
        "nameWhom": "Хмельницького  міськрайонного суду Хмельницької області",
        "index": "29000",
        "street": "вул. Героїв Майдану, буд. № 54",
        "mobile": "0(382)61-64-57"
    },
    {
        "fullName": "",
        "region": 0,
        "name": "",
        "nameWhom": "",
        "index": "",
        "street": "",
        "mobile": ""
    },
    {
        "fullName": "Новозаводський районний суд м.Чернігова",
        "region": 26,
        "name": "Новозаводський р/с м. Чернігова",
        "nameWhom": "Новозаводського районного суду м.Чернігова",
        "index": "14000",
        "street": "вул.Мстиславська, 17",
        "mobile": "0462-676-902"
    },
    {
        "fullName": "Господарський суд міста Києва",
        "region": 9,
        "name": "Господарський м. Києва",
        "nameWhom": "",
        "index": "01030",
        "street": "вул. Б. Хмельницького, 44-в",
        "mobile": ""
    },
    {
        "fullName": "Вінницький міський суд Вінницької обл.",
        "region": 1,
        "name": "Вінницький м/с",
        "nameWhom": "Вінницького міського суду Вінницької обл.",
        "index": "21050",
        "street": "вул. Грушевського, 17",
        "mobile": "(0432) 67-36-21"
    },
    {
        "fullName": "Білозерський районний суд Херсонської області",
        "region": 22,
        "name": "Білозерський р/с",
        "nameWhom": "Білозерського районного суду Херсонської області",
        "index": "75000",
        "street": "вул. Р.Вдовиченка,97",
        "mobile": "(05547) 3-39-00"
    },
    {
        "fullName": "Ленінський районний суд м. Миколаєва",
        "region": 14,
        "name": "Ленінський р/с Миколаєва",
        "nameWhom": "Ленінського районного суду м. Миколаєва",
        "index": "54018",
        "street": "вул. Космонавтів, 68 а",
        "mobile": "(0512) 55-95-00"
    },
    {
        "fullName": "Пустомитівський районний суд Львівської області",
        "region": 13,
        "name": "Пустомитівський р/с",
        "nameWhom": "Пустомитівського районного суду Львівської області",
        "index": "81100",
        "street": "вул. Івана Кандиби, 3",
        "mobile": "(03230) 4-11-59"
    },
    {
        "fullName": "Ковельський міськрайонний суд Волинської області",
        "region": 2,
        "name": "Ковельський міськрайсуд",
        "nameWhom": "Ковельського міськрайонного суду Волинської області",
        "index": "45008",
        "street": "вул. Незалежності, 15",
        "mobile": "(03352) 3-38-85,факс 5-90-66"
    },
    {
        "fullName": "Франківський районний суд м. Львова",
        "region": 13,
        "name": "Франківський райсуд",
        "nameWhom": "Франківського районного суду м. Львова",
        "index": "79034",
        "street": "вул.Героїв Крут, 1в",
        "mobile": "(032) 240-81-42"
    },
    {
        "fullName": "Києво-Святошинський районний суд Київської області",
        "region": 10,
        "name": "Києво-Святошинський р/с Київської обл.,",
        "nameWhom": "",
        "index": "03170",
        "street": "вул. Мельниченка , 1",
        "mobile": "(044) 424-31-54"
    },
    {
        "fullName": "",
        "region": 0,
        "name": "Феодосійський міський суд АР Крим",
        "nameWhom": "",
        "index": "",
        "street": "",
        "mobile": ""
    },
    {
        "fullName": "Господарський суд Київської області",
        "region": 9,
        "name": "Господарський суд Київської області",
        "nameWhom": "Господарського суду Київської області",
        "index": "01032",
        "street": "вул. Комінтерну, 16",
        "mobile": ""
    },
    {
        "fullName": "Красногвардійський районний суд м. Дніпропетровська",
        "region": 3,
        "name": "Красногвардійський р/с м.Дніпропетровська",
        "nameWhom": "",
        "index": "49006",
        "street": "пр-т Пушкіна, 77-б",
        "mobile": "(056) 371-27-02"
    },
    {
        "fullName": "Луцький міськрайонний суд Волинської обл.",
        "region": 2,
        "name": "Луцький міськрайсуд",
        "nameWhom": "Луцького міськрайонного суду Волинської обл.",
        "index": "43016",
        "street": "вул. Лесі Українки, 24",
        "mobile": "(0332) 72-22-04"
    },
    {
        "fullName": "Шепетівський міськрайонний суд",
        "region": 23,
        "name": "Шепетівський м/р",
        "nameWhom": "Шепетівського міськрайонного суду",
        "index": "30400",
        "street": "вул. Карла Маркса, буд. 30",
        "mobile": "0 3840 5 21 04"
    },
    {
        "fullName": "Свалявський районний суд Закарпатської області",
        "region": 6,
        "name": "Свалявський р/с",
        "nameWhom": "Свалявського районного суду Закарпатської області",
        "index": "89300",
        "street": "вул. Духновича, буд. 2",
        "mobile": "0 (233) 2-27-09"
    },
    {
        "fullName": "Прилуцький міськрайонний суд Чернігівської обл.",
        "region": 26,
        "name": "Прилуцький міськрайсуд",
        "nameWhom": "Прилуцькогоміськ районного суду Чернігівської обл.",
        "index": "17500",
        "street": "вул. Котляревського, 62",
        "mobile": "(04637)3-42-02,"
    },
    {
        "fullName": "Турійський районний суд Волинської обл.",
        "region": 2,
        "name": "Турійський райсуд",
        "nameWhom": "Турійського районного суду Волинської обл.",
        "index": "44800",
        "street": "вул. Луцька, 14",
        "mobile": "(03363) 2-13-31"
    },
    {
        "fullName": "Броварський міськрайонний суд Київської області",
        "region": 10,
        "name": "Броварський м/р",
        "nameWhom": "Броварського міськрайонного суду Київської області",
        "index": "07400",
        "street": "вул. Грушевського, буд. 2",
        "mobile": ""
    },
    {
        "fullName": "Обухівський районний суд Київської області",
        "region": 10,
        "name": "Обухівський р/с",
        "nameWhom": "Обухівського районного суду Київської області",
        "index": "08700",
        "street": "вул. Київська, буд. 20",
        "mobile": ""
    },
    {
        "fullName": "Комінтернівський районний суд м. Харкова",
        "region": 21,
        "name": "Комінтернівський р/с Харкова",
        "nameWhom": "Комінтернівського районного суду м. Харкова",
        "index": "61068",
        "street": "пров. Брянський, буд. 5",
        "mobile": ""
    },
    {
        "fullName": "Синельниківський міськрайонний суд Дніпропетровської області",
        "region": 3,
        "name": "Синельниківський м/р суд",
        "nameWhom": "Синельниківського міськрайонного суду Дніпропетровської області",
        "index": "52501",
        "street": "вул.Чехова,1",
        "mobile": "(05663) 4-39-92,4-39-96"
    },
    {
        "fullName": "Мукачівський міськрайонний суд Закарпатської області",
        "region": 6,
        "name": "Мукачівський мр/с Закарпатської",
        "nameWhom": "Мукачівського міськрайонного судг Закарпатської області",
        "index": "89600",
        "street": "вул. Л.Толстого, 13 (корпус №1)",
        "mobile": ""
    },
    {
        "fullName": "Южноукраїнський міський суд Миколаївської області",
        "region": 14,
        "name": "Южноукраїнський м/с",
        "nameWhom": "Южноукраїнського міського суду Миколаївської області",
        "index": "55000",
        "street": "вул. Дружби народів, 3a",
        "mobile": ""
    },
    {
        "fullName": "Господарський суд Дніпропетровської області",
        "region": 3,
        "name": "Господарський",
        "nameWhom": "",
        "index": "49600",
        "street": "вул. Куйбишева, буд. 1А",
        "mobile": ""
    },
    {
        "fullName": "Галицький районний суд м.Львова",
        "region": 13,
        "name": "Галицький р/с Львова",
        "nameWhom": "Галицького районного суду м.Львова",
        "index": "79018",
        "street": "вул. Чоловського, буд. 2",
        "mobile": ""
    },
    {
        "fullName": "Господарський суд Одеської обл.",
        "region": 15,
        "name": "Господарський суд Одеської обл.",
        "nameWhom": "Господарського суду Одеської обл.",
        "index": "65058",
        "street": "пр.Шевченка, 29",
        "mobile": "(0482)307-983"
    },
    {
        "fullName": "Фастівський міськрайонний суд Київської області",
        "region": 10,
        "name": "Фастівський мр/с Київської обл",
        "nameWhom": "Фастівського міськрайонного суду Київської області",
        "index": "08500",
        "street": "вул. Радянська, буд. 25",
        "mobile": ""
    },
    {
        "fullName": "Дзержинський районний суд м. Кривого Рогу",
        "region": 3,
        "name": "Дзержинський р/с Кривого Рогу",
        "nameWhom": "Дзержинського районного суду м. Кривого Рогу",
        "index": "50074",
        "street": "пр-т Миру, 24",
        "mobile": ""
    },
    {
        "fullName": "Камянець-Подільський міськрайонний суд Хмельницької області",
        "region": 23,
        "name": "Камянець Подільський м/р суд",
        "nameWhom": "Камянець-Подільського міськрайонного суду Хмельницької області",
        "index": "32300",
        "street": "вул. Шевченка, 29",
        "mobile": ""
    },
    {
        "fullName": "Ленінський районний суд міста Кіровограда",
        "region": 11,
        "name": "Ленінський р/с",
        "nameWhom": "Ленінського районного суду міста Кіровограда",
        "index": "25006",
        "street": "вул. Велика Перспективна, 40",
        "mobile": "(522) 22-78-71; 32-18-80;"
    },
    {
        "fullName": "Соснівський районний суд міста Черкаси",
        "region": 11,
        "name": "Соснівський р/с",
        "nameWhom": "Соснівського районного суду міста Черкаси",
        "index": "18000",
        "street": "вул. Гоголя, 316",
        "mobile": ""
    },
    {
        "fullName": "Тисменицький районний суд Івано-Франківської області",
        "region": 8,
        "name": "Тисменицький р/с",
        "nameWhom": "Тисменицького районного суду Івано-Франківської області",
        "index": "76002",
        "street": "вул. Незалежності, 150",
        "mobile": "(0342)78-10-33"
    },
    {
        "fullName": "Ленінський районний суд м.Дніпропетровськ",
        "region": 3,
        "name": "Ленінський р/с м.Дніпропетровськ",
        "nameWhom": "Ленінського районного суду м.Дніпропетровськ",
        "index": "49128",
        "street": "вул. Коробова, 6",
        "mobile": "(056) 370-77-51"
    },
    {
        "fullName": "Шевченківський районний суд м. Чернівці",
        "region": 25,
        "name": "Шевченківський р/с м. Чернівці",
        "nameWhom": "Шевченківського районного суду м. Чернівці",
        "index": "58000",
        "street": "вул. Кафедральна, 4",
        "mobile": "(0372) 55-17-02"
    },
    {
        "fullName": "Красилівський районний суд Хмельницької області",
        "region": 23,
        "name": "Красилівський р/с",
        "nameWhom": "Красилівського районного суду Хмельницької області",
        "index": "31000",
        "street": "вул. Булаєнка, буд. 4",
        "mobile": ""
    },
    {
        "fullName": "Жовківський районний суд Львівської області",
        "region": 13,
        "name": "Жовківський р/с",
        "nameWhom": "Жовківського районного суду Львівської області",
        "index": "80300",
        "street": "вул. Гагаріна, буд. 3а",
        "mobile": ""
    },
    {
        "fullName": "Центральний районний суд м.Сімферополя",
        "region": 0,
        "name": "Центральний р/с м.Сімферополя",
        "nameWhom": "Центрального районного суду м.Сімферополя",
        "index": "",
        "street": "",
        "mobile": ""
    },
    {
        "fullName": "Павлоградський міськрайонний суд Днепропетровської обл.",
        "region": 3,
        "name": "Павлоградський міськрайсуд",
        "nameWhom": "Павлоградського міськрайонного суду Днепропетровської обл.",
        "index": "51400",
        "street": "вул. Дніпровська, 135",
        "mobile": "(05632) 6-28-66"
    },
    {
        "fullName": "Орджонікідзевський міський суд Дніпропетровської обл.",
        "region": 3,
        "name": "Орджонікідзевський міссуд",
        "nameWhom": "Орджонікідзевського міського суду Дніпропетровської обл.",
        "index": "53300",
        "street": "вул. Петровського, 37",
        "mobile": "(05667) 4-38-86"
    },
    {
        "fullName": "Ленінський районний суд м.Запоріжжя",
        "region": 7,
        "name": "Ленінський райсуд Запоріжжя",
        "nameWhom": "Ленінського районного суду м.Запоріжжя",
        "index": "69006",
        "street": "вул. 40 років Радянської України, 1/2",
        "mobile": "(061) 283-08-13"
    },
    {
        "fullName": "Ківерцівський районний суд Волинської області",
        "region": 2,
        "name": "Ківерцівський р/с",
        "nameWhom": "Ківерцівського районного суду Волинської області",
        "index": "45200",
        "street": "вул. Грушевського, 20",
        "mobile": "(03365) 2-16-40"
    },
    {
        "fullName": "Господарський суд Житомирської області",
        "region": 5,
        "name": "Господарський суд Житомирської обл.",
        "nameWhom": "Господарського суду Житомирської області",
        "index": "10002",
        "street": "майдан Путятинський, 3/65",
        "mobile": "(0412) 48-16-25"
    },
    {
        "fullName": "Фрунзенський районний суд м. Харкова",
        "region": 21,
        "name": "Фрунзенський районний суд м. Харкова",
        "nameWhom": "Фрунзенського районного суду м. Харкова",
        "index": "61099",
        "street": "бул. Б.Хмельницького, 32/38",
        "mobile": "(057) 392-13-54"
    },
    {
        "fullName": "Золотоніський міськрайонний суд Черкаської області",
        "region": 14,
        "name": "Золотоніський р/с",
        "nameWhom": "Золотоніського міськрайонного суду Черкаської області",
        "index": "19700",
        "street": "вул. Шевченка, 76",
        "mobile": "(04737) 5-26-10"
    },
    {
        "fullName": "Суворовський районний суд м. Одеси",
        "region": 15,
        "name": "Суворовський р/с  м. Одеси",
        "nameWhom": "Суворовського районного суду м. Одеси",
        "index": "65003",
        "street": "вул. Чорноморського козацтва, 68",
        "mobile": "048-785-68-37, 048-723-33-77"
    },
    {
        "fullName": "Кілійський районний суд Одеської області",
        "region": 15,
        "name": "Кілійський р/с Одеської області",
        "nameWhom": "Кілійського районного суду Одеської області",
        "index": "68300",
        "street": "вул. Леніна, 19",
        "mobile": ""
    },
    {
        "fullName": "Калинівський районний суд Вінницької області",
        "region": 1,
        "name": "Калинівський р/с",
        "nameWhom": "Калинівського районного суду Вінницької області",
        "index": "22400",
        "street": "вул. Дзержинського, 70",
        "mobile": ""
    },
    {
        "fullName": "Новоград-Волинський міськрайонний суд Житомирської області",
        "region": 5,
        "name": "Новоград-Волинський м/с Житомирської області",
        "nameWhom": "Новоград-Волинського міськрайонного суду Житомирської області",
        "index": "11700",
        "street": "вул. І. Франка, 31",
        "mobile": ""
    },
    {
        "fullName": "Ковпаківський районний суд м. Сум",
        "region": 19,
        "name": "Ковпаківський р/с м. Сум",
        "nameWhom": "Ковпаківського районного суду м. Сумм",
        "index": "40009",
        "street": "вул. Першотравнева, буд. 12",
        "mobile": ""
    },
    {
        "fullName": "Бердичівський міськрайонний суд Житомирської області",
        "region": 5,
        "name": "Бердичівський мр/с",
        "nameWhom": "Бердичівського міськрайонного суду Житомирської області",
        "index": "13312",
        "street": "вул. Житомирська, буд. 30-а",
        "mobile": ""
    },
    {
        "fullName": "Жовтневий районний суд м. Кривого Рогу",
        "region": 3,
        "name": "Жовтневий р/с м. Кривого Рогу",
        "nameWhom": "Жовтневого районного суду м. Кривого Рогу",
        "index": "50029",
        "street": "вул. Невська, 3",
        "mobile": ""
    },
    {
        "fullName": "Сарненський районний суд Рівненської області",
        "region": 17,
        "name": "Сарненський р/с",
        "nameWhom": "Сарненського районного суду Рівненської області",
        "index": "34500",
        "street": "вул. Залоги, 5",
        "mobile": "(03655) 3-26-41"
    },
    {
        "fullName": "Коломийський міськрайонний суд Івано-Франківської області",
        "region": 8,
        "name": "Коломийський р/с",
        "nameWhom": "Коломийського міськрайонного суду Івано-Франківської області",
        "index": "78200",
        "street": "пр-т Грушевського, 29",
        "mobile": "(03433) 4-71-98"
    },
    {
        "fullName": "Житомирський районний суд Житомирської області",
        "region": 5,
        "name": "Житомирський р/с",
        "nameWhom": "Житомирського районного суду Житомирської області",
        "index": "10031",
        "street": "вул. Щорса, 92",
        "mobile": ""
    },
    {
        "fullName": "Біляївський районний суд Одеської області",
        "region": 15,
        "name": "Біляївський р/с Одеської області",
        "nameWhom": "Біляївського районного суду Одеської області",
        "index": "67600",
        "street": "вул. Кіпенко, 1",
        "mobile": ""
    },
    {
        "fullName": "Первомайський міськрайонний суд Харківської області",
        "region": 21,
        "name": "Первомайський мр/с",
        "nameWhom": "Первомайського міськрайонного суду Харківської області",
        "index": "64107",
        "street": "вул. Леніна, буд. 18",
        "mobile": ""
    },
    {
        "fullName": "Калуський міськрайонний суд Івано-Франківської області",
        "region": 8,
        "name": "Калуський м.р/с",
        "nameWhom": "Калуського міськрайонного суду Івано-Франківської області",
        "index": "77300",
        "street": "вул. Молодіжна,10",
        "mobile": ""
    },
    {
        "fullName": "Харківський районний суд Харківської області",
        "region": 21,
        "name": "Харківський р/с",
        "nameWhom": "Харківського районного суду Харківської області",
        "index": "62458",
        "street": "вул. Калініна, 18",
        "mobile": ""
    },
    {
        "fullName": "Лубенський міськрайонний суд Полтавської області",
        "region": 16,
        "name": "Лубенський мр/с Полтавської області",
        "nameWhom": "Лубенського міськрайонного суду Полтавської області",
        "index": "37500",
        "street": "вул. Монастирська , 17",
        "mobile": ""
    },
    {
        "fullName": "Переяслав-Хмельницький міськрайонний суд Київської області",
        "region": 10,
        "name": "Переяслав-Хмельницький м/р суд Київ.обл.",
        "nameWhom": "Переяслав-Хмельницького міськрайонного суду Київської області",
        "index": "08400",
        "street": "вул. Б.Хмельницького, 65",
        "mobile": "(04567) 5-15-18, 5-25-52, 5-13-39"
    },
    {
        "fullName": "Орджонікідзевський районний суд м. Харкова",
        "region": 21,
        "name": "Орджонікідзевський р/с м. Харкова",
        "nameWhom": "Орджонікідзевського районного суду м. Харкова",
        "index": "61007",
        "street": "проспект Орджонікідзе, 7",
        "mobile": "(0572) 93-50-23"
    },
    {
        "fullName": "Кролевецький районний суд Сумської області",
        "region": 19,
        "name": "Кролевецький р/н суд Сумської області",
        "nameWhom": "Кролевецького районного суду Сумської області",
        "index": "41300",
        "street": "вул. Франка, 13",
        "mobile": "(05453) 9 54 47, 9 74 45"
    },
    {
        "fullName": "Нижньосірогозький районний суд Херсонської області!",
        "region": 22,
        "name": "Нижньосірогозький районний суд Херсонської обл",
        "nameWhom": "Нижньосірогозького районного суду Херсонської області",
        "index": "74701",
        "street": "вул. Чкалова, буд. № 6",
        "mobile": ""
    },
    {
        "fullName": "Нижньосірогозький районний суд Херсонської області!",
        "region": 22,
        "name": "Нижньосірогозький районний суд Херсонської обл",
        "nameWhom": "Нижньосірогозького районного суду Херсонської області",
        "index": "74701",
        "street": "вул. Чкалова, буд. № 6",
        "mobile": ""
    }
]